{"components_react_overview.md":"B8t1eq47","config_index.md":"Dhq3m3XM","components_react_autocomplete.md":"BBkLquKs","guide_what-is-this.md":"ByXzBlLw","index.md":"3E7OihZp","guide_getting-started.md":"DTrD7hGR","zh_components_dom_overview.md":"Dpl0q2g2","zh_components_dom_autocomplete.md":"5-OGp4ry","components_dom_autocomplete.md":"CsNSYpr-","zh_components_react_overview.md":"Cqo2rDYt","components_vue_overview.md":"BJy70NQV","zh_components_vue_autocomplete.md":"B7c1uHZ4","components_dom_overview.md":"Bs35aTRz","zh_index.md":"L2LiX_ee","components_vue_autocomplete.md":"CX980KzP","zh_guide_what-is-this.md":"BGMjBqSE","zh_components_vue_overview.md":"Cvoe2l3y","zh_guide_getting-started.md":"BMXkwOS6","zh_components_react_autocomplete.md":"DysP36Jk","zh_guide_example.md":"DxhRYlXs","zh_config_index.md":"Byl0XFhX"}
