{"config_index.md":"WQonKvv0","zh_guide_example.md":"7BBq4TSD","index.md":"mXKRlAAw","zh_components_vue_overview.md":"x-ZW8sG8","components_vue_overview.md":"B0fDrieL","zh_guide_getting-started.md":"-rMNsJJD","components_vue_autocomplete.md":"DwOJ1AwW","zh_components_vue_autocomplete.md":"CyEE498l","zh_components_react_autocomplete.md":"Dl9EVLNZ","zh_components_react_overview.md":"OPrjwEV-","zh_index.md":"DSBTT9oH","components_react_overview.md":"DwJwfo5X","guide_what-is-this.md":"CHIYQIf8","components_react_autocomplete.md":"3HqtmSO8","guide_getting-started.md":"CP11aCrc","components_dom_overview.md":"BrHDTn0a","components_dom_autocomplete.md":"BvdUUk8S","zh_components_dom_autocomplete.md":"fKfjvueL","zh_guide_what-is-this.md":"CBbdkOex","zh_components_dom_overview.md":"DlhWgyMi","zh_config_index.md":"BYCQwprE"}
